setup.py
shaheen_distributions/Binomialdistribution.py
shaheen_distributions/Gaussiandistribution.py
shaheen_distributions/Generaldistribution.py
shaheen_distributions/__init__.py
shaheen_distributions.egg-info/PKG-INFO
shaheen_distributions.egg-info/SOURCES.txt
shaheen_distributions.egg-info/dependency_links.txt
shaheen_distributions.egg-info/not-zip-safe
shaheen_distributions.egg-info/top_level.txt