Metadata-Version: 1.0
Name: shaheen-distributions
Version: 0.2
Summary: Gaussian distributions
Home-page: UNKNOWN
Author: talha3111997
Author-email: UNKNOWN
License: UNKNOWN
Platform: UNKNOWN
